CanvasPlus/__init__.py
CanvasPlus/_errors.py
CanvasPlus/canvasplus.py
CanvasPlus/pythonBelow35.py
CanvasPlus/templates.py
CanvasPlus/assets/__init__.py
CanvasPlus/assets/asynctransformations.py
CanvasPlus/assets/transformations.py
CanvasPlus/assets/widgetwindows.py
CanvasPlus/pythonBelow35Assets/__init__.py
CanvasPlus/pythonBelow35Assets/asynctransformations.py
CanvasPlus/pythonBelow35Assets/transformations.py
CanvasPlus/pythonBelow35Assets/widgetwindows.py
canvasplus-1.4.1.dist-info/LICENSE
canvasplus-1.4.1.dist-info/METADATA
canvasplus-1.4.1.dist-info/WHEEL
canvasplus-1.4.1.dist-info/top_level.txt
canvasplus-1.4.1.dist-info/RECORD
