Metadata-Version: 2.1
Name: canvasplus
Version: 1.4.1
Summary: Improved Canvas widget for tkinter with more functionality to display graphical elements like lines or text. 
Home-page: https://github.com/Luke-zhang-04/CanvasPlus
Author: Luke Zhang
Author-email: luke.zhang2004@gmail.com
License: UNKNOWN
Platform: UNKNOWN
Classifier: Development Status :: 5 - Production/Stable
Classifier: Programming Language :: Python :: 3.3
Classifier: Programming Language :: Python :: 3.4
Classifier: Programming Language :: Python :: 3.5
Classifier: Programming Language :: Python :: 3.6
Classifier: Programming Language :: Python :: 3.7
Classifier: Programming Language :: Python :: 3.8
Classifier: Programming Language :: Python :: 3.9
Classifier: Programming Language :: Tcl
Classifier: Topic :: Multimedia :: Graphics
Classifier: License :: OSI Approved :: MIT License
Classifier: Operating System :: OS Independent
Requires-Python: >=3.3
Requires-Dist: asyncio (>=3.4.3)
